mod_trl-0.20.0.dev0.dist-info/licenses/LICENSE
trl/__init__.py
trl/cli.py
trl/core.py
trl/data_utils.py
trl/import_utils.py
trl/mergekit_utils.py
trl/accelerate_configs/fsdp1.yaml
trl/accelerate_configs/fsdp2.yaml
trl/accelerate_configs/multi_gpu.yaml
trl/accelerate_configs/single_gpu.yaml
trl/accelerate_configs/zero1.yaml
trl/accelerate_configs/zero2.yaml
trl/accelerate_configs/zero3.yaml
trl/environment/__init__.py
trl/environment/base_environment.py
trl/extras/__init__.py
trl/extras/best_of_n_sampler.py
trl/extras/dataset_formatting.py
trl/extras/injected_process_group.py
trl/extras/profiling.py
trl/extras/vllm_client.py
trl/models/__init__.py
trl/models/activation_offloading.py
trl/models/auxiliary_modules.py
trl/models/modeling_base.py
trl/models/modeling_sd_base.py
trl/models/modeling_value_head.py
trl/models/sd_utils.py
trl/models/utils.py
trl/rewards/__init__.py
trl/rewards/format_rewards.py
trl/scripts/__init__.py
trl/scripts/dpo.py
trl/scripts/env.py
trl/scripts/grpo.py
trl/scripts/kto.py
trl/scripts/sft.py
trl/scripts/utils.py
trl/scripts/vllm_serve.py
trl/templates/lm_model_card.md
trl/trainer/__init__.py
trl/trainer/alignprop_config.py
trl/trainer/alignprop_trainer.py
trl/trainer/bco_config.py
trl/trainer/bco_trainer.py
trl/trainer/callbacks.py
trl/trainer/cpo_config.py
trl/trainer/cpo_trainer.py
trl/trainer/ddpo_config.py
trl/trainer/ddpo_trainer.py
trl/trainer/dpo_config.py
trl/trainer/dpo_trainer.py
trl/trainer/gkd_config.py
trl/trainer/gkd_trainer.py
trl/trainer/grpo_config.py
trl/trainer/grpo_trainer.py
trl/trainer/iterative_sft_config.py
trl/trainer/iterative_sft_trainer.py
trl/trainer/judges.py
trl/trainer/kto_config.py
trl/trainer/kto_trainer.py
trl/trainer/model_config.py
trl/trainer/nash_md_config.py
trl/trainer/nash_md_trainer.py
trl/trainer/online_dpo_config.py
trl/trainer/online_dpo_trainer.py
trl/trainer/orpo_config.py
trl/trainer/orpo_trainer.py
trl/trainer/ppo_config.py
trl/trainer/ppo_trainer.py
trl/trainer/prm_config.py
trl/trainer/prm_trainer.py
trl/trainer/reward_config.py
mod_trl-0.20.0.dev0.dist-info/METADATA
mod_trl-0.20.0.dev0.dist-info/WHEEL
mod_trl-0.20.0.dev0.dist-info/entry_points.txt
mod_trl-0.20.0.dev0.dist-info/top_level.txt
mod_trl-0.20.0.dev0.dist-info/RECORD
