Metadata-Version: 2.4
Name: mod-trl
Version: 0.20.0.dev0
Summary: Train transformer language models with reinforcement learning.
Home-page: https://github.com/huggingface/trl
Author: Leandro von Werra
Author-email: leandro.vonwerra@gmail.com
Keywords: transformers,huggingface,language modeling,post-training,rlhf,sft,dpo,grpo
Classifier: Development Status :: 2 - Pre-Alpha
Classifier: Intended Audience :: Developers
Classifier: Intended Audience :: Science/Research
Classifier: Natural Language :: English
Classifier: Operating System :: OS Independent
Classifier: Programming Language :: Python :: 3
Classifier: Programming Language :: Python :: 3.9
Classifier: Programming Language :: Python :: 3.10
Classifier: Programming Language :: Python :: 3.11
Classifier: Programming Language :: Python :: 3.12
Classifier: Programming Language :: Python :: 3.13
Requires-Python: >=3.9
License-File: LICENSE
Requires-Dist: accelerate>=1.4.0
Requires-Dist: datasets>=3.0.0
Requires-Dist: transformers>=4.51.0
Provides-Extra: bco
Requires-Dist: scikit-learn; extra == "bco"
Requires-Dist: joblib; extra == "bco"
Provides-Extra: deepspeed
Requires-Dist: deepspeed>=0.14.4; extra == "deepspeed"
Provides-Extra: diffusers
Requires-Dist: diffusers>=0.18.0; extra == "diffusers"
Provides-Extra: judges
Requires-Dist: openai>=1.23.2; extra == "judges"
Requires-Dist: llm-blender>=0.0.2; extra == "judges"
Provides-Extra: liger
Requires-Dist: liger-kernel>=0.5.9; extra == "liger"
Provides-Extra: peft
Requires-Dist: peft>=0.8.0; extra == "peft"
Provides-Extra: quantization
Requires-Dist: bitsandbytes; extra == "quantization"
Provides-Extra: scikit
Requires-Dist: scikit-learn; extra == "scikit"
Provides-Extra: test
Requires-Dist: parameterized; extra == "test"
Requires-Dist: pytest-cov; extra == "test"
Requires-Dist: pytest-rerunfailures; extra == "test"
Requires-Dist: pytest-xdist; extra == "test"
Requires-Dist: pytest; extra == "test"
Provides-Extra: vllm
Requires-Dist: vllm>=0.8.3; python_version < "3.13" and extra == "vllm"
Requires-Dist: fastapi; python_version < "3.13" and extra == "vllm"
Requires-Dist: pydantic; python_version < "3.13" and extra == "vllm"
Requires-Dist: requests; python_version < "3.13" and extra == "vllm"
Requires-Dist: uvicorn; python_version < "3.13" and extra == "vllm"
Provides-Extra: vlm
Requires-Dist: Pillow; extra == "vlm"
Provides-Extra: dev
Requires-Dist: scikit-learn; extra == "dev"
Requires-Dist: joblib; extra == "dev"
Requires-Dist: deepspeed>=0.14.4; extra == "dev"
Requires-Dist: diffusers>=0.18.0; extra == "dev"
Requires-Dist: openai>=1.23.2; extra == "dev"
Requires-Dist: llm-blender>=0.0.2; extra == "dev"
Requires-Dist: liger-kernel>=0.5.9; extra == "dev"
Requires-Dist: peft>=0.8.0; extra == "dev"
Requires-Dist: bitsandbytes; extra == "dev"
Requires-Dist: scikit-learn; extra == "dev"
Requires-Dist: parameterized; extra == "dev"
Requires-Dist: pytest-cov; extra == "dev"
Requires-Dist: pytest-rerunfailures; extra == "dev"
Requires-Dist: pytest-xdist; extra == "dev"
Requires-Dist: pytest; extra == "dev"
Requires-Dist: Pillow; extra == "dev"
Dynamic: license-file
